__init__.py
d365_relations_mcp/__init__.py
d365_relations_mcp/config.py
d365_relations_mcp/main.py
d365_relations_mcp/tools.py
d365_relations_mcp-0.1.3.dist-info/licenses/LICENSE
d365_relations_mcp-0.1.3.dist-info/METADATA
d365_relations_mcp-0.1.3.dist-info/WHEEL
d365_relations_mcp-0.1.3.dist-info/entry_points.txt
d365_relations_mcp-0.1.3.dist-info/top_level.txt
d365_relations_mcp-0.1.3.dist-info/RECORD
