Metadata-Version: 2.4
Name: d365-relations-mcp
Version: 0.1.3
Summary: MCP server for Dynamics 365 Table Relationship Explorer
Author: duggurd
Requires-Python: >=3.10
License-File: LICENSE
Requires-Dist: fastmcp>=0.1.0
Requires-Dist: d365-relations-cli>=0.1.4
Dynamic: license-file
